MapExtrackt/__init__.py
MapExtrackt/extractor.py
MapExtrackt/functions.py
mapextrackt-0.4.8.6.dist-info/LICENCE
mapextrackt-0.4.8.6.dist-info/METADATA
mapextrackt-0.4.8.6.dist-info/WHEEL
mapextrackt-0.4.8.6.dist-info/top_level.txt
mapextrackt-0.4.8.6.dist-info/RECORD
