Metadata-Version: 2.1
Name: mapextrackt
Version: 0.4.8.6
Summary: Pytorch Feature Map Extractor
Home-page: https://github.com/lewis-morris/mapextrackt
Author: Lewis Morris
Author-email: lewis.morris@gmail.com
License: MIT
Platform: UNKNOWN
